{
  "chobble": {
    "name": "Chobble Tickets",
    "annual_cost": 50,
    "per_ticket_fee_percent": 0,
    "per_ticket_fee_fixed": 0,
    "payment_processing_percent": 1.5,
    "payment_processing_fixed": 0.2
  },
  "eventbrite": {
    "name": "Eventbrite",
    "annual_cost": 0,
    "per_ticket_fee_percent": 6.95,
    "per_ticket_fee_fixed": 0.59,
    "payment_processing_percent": 0,
    "payment_processing_fixed": 0,
    "fee_note": "Eventbrite fees: 6.95% + £0.59 per ticket (includes payment processing). Chobble Tickets: £50/year flat + Stripe processing (1.5% + 20p)."
  },
  "bookitbee": {
    "name": "BookitBee",
    "annual_cost": 0,
    "per_ticket_fee_percent": 3.5,
    "per_ticket_fee_fixed": 0,
    "payment_processing_percent": 1.5,
    "payment_processing_fixed": 0.2,
    "fee_note": "BookitBee fees: from 3.5% per ticket (up to 6.5% for advanced features), min £1, max £19.95 cap, plus Stripe processing (1.5% + 20p). Chobble Tickets: £50/year flat + Stripe processing (1.5% + 20p). Source: bookitbee.com/pricing-uk (March 2026)."
  },
  "parentkind": {
    "name": "Parentkind",
    "annual_cost": 121,
    "per_ticket_fee_percent": 3.95,
    "per_ticket_fee_fixed": 0,
    "payment_processing_percent": 1.5,
    "payment_processing_fixed": 0.2,
    "fee_note": "Parentkind costs: from £121/year membership (by Direct Debit, schools ≤100 pupils; £171 for 101+ pupils) + 3.95% platform fee per transaction on the Starter plan (1.5% on Premium at £299.99+VAT/year) + Stripe processing (1.5% + 20p). Chobble Tickets: £50/year flat (£25 for community groups) + Stripe processing (1.5% + 20p). Source: parentkind.org.uk/pta-membership-fee-update (November 2025)."
  },
  "ticketmaster": {
    "name": "Ticketmaster",
    "annual_cost": 0,
    "per_ticket_fee_percent": 10,
    "per_ticket_fee_fixed": 2.5,
    "payment_processing_percent": 0,
    "payment_processing_fixed": 0,
    "fee_note": "Ticketmaster fees vary by event and venue — this estimate uses approximately 10% + £2.50 per ticket (bundled). Actual fees may be higher or lower. Chobble Tickets: £50/year flat + Stripe processing (1.5% + 20p)."
  },
  "hi_events": {
    "name": "Hi.Events",
    "annual_cost": 0,
    "per_ticket_fee_percent": 0.75,
    "per_ticket_fee_fixed": 0.32,
    "payment_processing_percent": 1.5,
    "payment_processing_fixed": 0.2,
    "fee_note": "Hi.Events cloud fees: 0.75% + ~32p per ticket, plus Stripe processing (1.5% + 20p). Self-hosted Hi.Events has no platform fees, only Stripe processing. Chobble Tickets: £50/year flat + Stripe processing (1.5% + 20p)."
  },
  "hi_events_selfhosted": {
    "name": "Hi.Events Self-Hosted",
    "annual_cost": 420,
    "per_ticket_fee_percent": 0,
    "per_ticket_fee_fixed": 0,
    "payment_processing_percent": 1.5,
    "payment_processing_fixed": 0.2,
    "fee_note": "Hi.Events Single Domain commercial license: $499 (approx. £420). AGPL edition is free but requires 'Powered by Hi.Events' branding. Multi-tenant licenses available at higher tiers — contact Hi.Events for pricing. Chobble Tickets self-hosted: free, no license fee + Stripe processing (1.5% + 20p). Source: hi.events/pricing and hi.events/open-source-event-ticketing (March 2026)."
  },
  "pretix_hosted": {
    "name": "Pretix Hosted",
    "annual_cost": 0,
    "per_ticket_fee_percent": 2.5,
    "per_ticket_fee_fixed": 0,
    "payment_processing_percent": 1.5,
    "payment_processing_fixed": 0.2,
    "fee_note": "Pretix Hosted fees: 2.5% of ticket price excl. taxes (capped at ~£13/ticket). Payment processing (e.g. Stripe 1.5% + 20p) is separate. Chobble Tickets: £50/year flat + Stripe processing (1.5% + 20p)."
  },
  "pretix_selfhosted": {
    "name": "Pretix Enterprise",
    "annual_cost": 420,
    "per_ticket_fee_percent": 0,
    "per_ticket_fee_fixed": 0,
    "payment_processing_percent": 1.5,
    "payment_processing_fixed": 0.2,
    "fee_note": "Pretix Enterprise Starter license: €499/year (approx. £420). Community edition is free but lacks proprietary plugins. Chobble Tickets self-hosted: free, no license fee + Stripe processing (1.5% + 20p)."
  },
  "chobble_selfhosted": {
    "name": "Chobble Tickets",
    "annual_cost": 0,
    "per_ticket_fee_percent": 0,
    "per_ticket_fee_fixed": 0,
    "payment_processing_percent": 1.5,
    "payment_processing_fixed": 0.2
  }
}
